mflux_ai/__init__.py
mflux_ai/core.py
mflux_ai/mflux_ai.py
mflux_ai-0.7.0.dist-info/AUTHORS.rst
mflux_ai-0.7.0.dist-info/LICENSE
mflux_ai-0.7.0.dist-info/METADATA
mflux_ai-0.7.0.dist-info/WHEEL
mflux_ai-0.7.0.dist-info/top_level.txt
mflux_ai-0.7.0.dist-info/RECORD
