Metadata-Version: 2.1
Name: mflux-ai
Version: 0.7.0
Summary: The Python client for MFlux.ai
Home-page: https://github.com/AIAScience/mflux-ai-python
Author: AIA Science AS
Author-email: mflux.ai@aiascience.com
License: Apache License 2.0
Keywords: mflux_ai mlflow ml tracking ai workflow machine learning object storage dataset versioning
Platform: UNKNOWN
Classifier: Development Status :: 4 - Beta
Classifier: Intended Audience :: Developers
Classifier: License :: OSI Approved :: Apache Software License
Classifier: Natural Language :: English
Classifier: Programming Language :: Python :: 3.5
Classifier: Programming Language :: Python :: 3.6
Classifier: Programming Language :: Python :: 3.7
Classifier: Topic :: Scientific/Engineering :: Artificial Intelligence
Classifier: Topic :: Software Development :: Version Control
Requires-Python: >=3.5, <4
Requires-Dist: joblib (<1)
Requires-Dist: minio (<5,>=4)
Requires-Dist: mlflow (<2,>=1.2.0)
Requires-Dist: requests
